randflow/__init__.py
randflow/generator.py
randflow/point.py
randflow/spectrum.py
randflow-0.0.1.dist-info/METADATA
randflow-0.0.1.dist-info/WHEEL
randflow-0.0.1.dist-info/license_files/LICENSE
randflow-0.0.1.dist-info/RECORD
