Metadata-Version: 2.1
Name: randflow
Version: 0.0.1
Summary: A random flow generator for large eddy simulation of atmosphere boundary layer.
Project-URL: Homepage, https://github.com/sunjp704/randflow
Project-URL: Bug Tracker, https://github.com/sunjp704/randflow/issues
Author-email: Sun Jianping <sunjianping@zju.edu.cn>
License: Copyright (c) 2018 The Python Packaging Authority
Classifier: License :: OSI Approved :: MIT License
Classifier: Operating System :: OS Independent
Classifier: Programming Language :: Python :: 3
Requires-Python: >=3.7
